mahi/__init__.py
mahi-0.1.dist-info/LICENCE.txt
mahi-0.1.dist-info/METADATA
mahi-0.1.dist-info/WHEEL
mahi-0.1.dist-info/top_level.txt
mahi-0.1.dist-info/RECORD
