Metadata-Version: 2.1
Name: mahi
Version: 0.1
Summary: This is just for printing  Author name
Author: Mahesh N D
Author-email: mahibhahadur@gmail.com
Classifier: Programming Language :: Python :: 3
Classifier: License :: OSI Approved :: MIT License
Classifier: Operating System :: OS Independent
License-File: LICENCE.txt
